CHANGES.rst
CONTRIBUTORS.rst
MANIFEST.in
README.rst
VERSION
pyproject.toml
setup.cfg
setup.py
test.rst
docs/index.rst
src/pdfreactor/__init__.py
src/pdfreactor.parsecfg.egg-info/PKG-INFO
src/pdfreactor.parsecfg.egg-info/SOURCES.txt
src/pdfreactor.parsecfg.egg-info/dependency_links.txt
src/pdfreactor.parsecfg.egg-info/entry_points.txt
src/pdfreactor.parsecfg.egg-info/namespace_packages.txt
src/pdfreactor.parsecfg.egg-info/not-zip-safe
src/pdfreactor.parsecfg.egg-info/requires.txt
src/pdfreactor.parsecfg.egg-info/top_level.txt
src/pdfreactor/parsecfg/__init__.py
src/pdfreactor/parsecfg/_args.py
src/pdfreactor/parsecfg/_configkeys.py
src/pdfreactor/parsecfg/_statement.py
src/pdfreactor/parsecfg/_tokeninfo.py
src/pdfreactor/parsecfg/_tokensgroup.py
src/pdfreactor/parsecfg/configure.zcml
src/pdfreactor/parsecfg/convert.py
src/pdfreactor/parsecfg/defaults.py
src/pdfreactor/parsecfg/oldmethods.py
src/pdfreactor/parsecfg/oldsymbols.py
src/pdfreactor/parsecfg/parse.py
src/pdfreactor/parsecfg/profiles.zcml
src/pdfreactor/parsecfg/setuphandlers.py
src/pdfreactor/parsecfg/symbols.py
src/pdfreactor/parsecfg/plone/__init__.py
src/pdfreactor/parsecfg/plone/controlpanel.py
src/pdfreactor/parsecfg/plone/interfaces.py
src/pdfreactor/parsecfg/plone/parsed.py
src/pdfreactor/parsecfg/profiles/default/controlpanel.xml
src/pdfreactor/parsecfg/profiles/default/metadata.xml